bonesistools/__init__.py
bonesistools/boolpy/__init__.py
bonesistools/boolpy/_algebra.py
bonesistools/boolpy/_bnet.py
bonesistools/boolpy/_boolean.py
bonesistools/boolpy/_hypercube.py
bonesistools/boolpy/_typing.py
bonesistools/databases/__init__.py
bonesistools/databases/_typing.py
bonesistools/databases/ncbi/__init__.py
bonesistools/databases/ncbi/_genesyn.py
bonesistools/databases/ncbi/data/gi/escherichia_coli_gene_info.tsv
bonesistools/databases/ncbi/data/gi/homo_sapiens_gene_info.tsv
bonesistools/databases/ncbi/data/gi/mus_musculus_gene_info.tsv
bonesistools/databases/omnipath/__init__.py
bonesistools/databases/omnipath/_collectri.py
bonesistools/databases/omnipath/_dorothea.py
bonesistools/grntools/__init__.py
bonesistools/grntools/_algorithms.py
bonesistools/grntools/_graphinfo.py
bonesistools/grntools/_typing.py
bonesistools/grntools/graph_analysis.py
bonesistools/sctools/__init__.py
bonesistools/sctools/_typing.py
bonesistools/sctools/plotting/__init__.py
bonesistools/sctools/plotting/_boxplot.py
bonesistools/sctools/plotting/_colors.py
bonesistools/sctools/plotting/_figure.py
bonesistools/sctools/plotting/_graphplot.py
bonesistools/sctools/plotting/_kde.py
bonesistools/sctools/plotting/_scatterplot.py
bonesistools/sctools/plotting/_typing.py
bonesistools/sctools/preprocessing/__init__.py
bonesistools/sctools/preprocessing/_genename.py
bonesistools/sctools/preprocessing/_simple.py
bonesistools/sctools/tools/__init__.py
bonesistools/sctools/tools/_classification.py
bonesistools/sctools/tools/_conversion.py
bonesistools/sctools/tools/_graph.py
bonesistools/sctools/tools/_markers.py
bonesistools/sctools/tools/_maths.py
bonesistools/sctools/tools/_neighbors.py
bonesistools/sctools/tools/_utils.py
bonesistools/sctools/tools/_write.py
bonesistools-1.1.5.dist-info/METADATA
bonesistools-1.1.5.dist-info/WHEEL
bonesistools-1.1.5.dist-info/licenses/LICENSE
bonesistools-1.1.5.dist-info/RECORD
