Metadata-Version: 2.4
Name: bonesistools
Version: 1.1.5
Summary: BoNesisTools is a python package proposing bioinformatics tools for upstream and downstream analysis of BoNesis framework
Project-URL: Repository, https://github.com/bnediction/bonesistools
Author: Théo Roncalli
Maintainer-email: Théo Roncalli <theo.roncalli@labri.fr>
License: 
License-File: LICENSE
Keywords: anndata,atacseq,bioinformatics,bonesis,boolean-networks,gene-regulatory-networks,mudata,rnaseq,single-cell,systems-biology
Classifier: Development Status :: 3 - Alpha
Classifier: Environment :: Console
Classifier: Framework :: IPython
Classifier: Framework :: Matplotlib
Classifier: Intended Audience :: Developers
Classifier: Intended Audience :: Science/Research
Classifier: License :: OSI Approved :: CEA CNRS Inria Logiciel Libre License, version 2.1 (CeCILL-2.1)
Classifier: Natural Language :: English
Classifier: Operating System :: MacOS :: MacOS X
Classifier: Operating System :: Microsoft :: Windows
Classifier: Operating System :: POSIX :: Linux
Classifier: Operating System :: Unix
Classifier: Programming Language :: Python :: 3.7
Classifier: Programming Language :: Python :: 3.8
Classifier: Programming Language :: Python :: 3.9
Classifier: Programming Language :: Python :: 3.10
Classifier: Programming Language :: Python :: 3.11
Classifier: Programming Language :: Python :: 3.12
Classifier: Programming Language :: Python :: 3.13
Classifier: Topic :: Scientific/Engineering :: Bio-Informatics
Classifier: Topic :: Scientific/Engineering :: Visualization
Classifier: Topic :: Software Development :: Libraries :: Python Modules
Requires-Python: >=3.7
Requires-Dist: anndata>=0.8
Requires-Dist: h5py>=3.7
Requires-Dist: matplotlib>=3.5
Requires-Dist: networkx>=2.1
Requires-Dist: numpy>=1.21
Requires-Dist: pandas>=1.3.5
Requires-Dist: scikit-learn>=1.0
Requires-Dist: scipy>=1.7
Provides-Extra: collectri
Requires-Dist: decoupler>=1.8; extra == 'collectri'
Provides-Extra: default
Requires-Dist: boolean-py>=4.0; extra == 'default'
Requires-Dist: decoupler>=1.8; extra == 'default'
Requires-Dist: mpbn>=3.3; extra == 'default'
Requires-Dist: mudata>=0.3.1; extra == 'default'
Requires-Dist: multiprocess>=0.70.18; extra == 'default'
Requires-Dist: pydot>=3.0.2; extra == 'default'
Provides-Extra: mpbn
Requires-Dist: mpbn>=4.1; extra == 'mpbn'
Provides-Extra: mudata
Requires-Dist: mudata>=0.3.1; extra == 'mudata'
